/*     */ package facade.characters.wmedef;
/*     */ 
/*     */ import wm.WME;
/*     */ 
/*     */ 
/*     */ 
/*     */ 
/*     */ 
/*     */ 
/*     */ public class PostBeatMixinInfoWME
/*     */   extends WME
/*     */ {
/*     */   private int beatGGreetsP;
/*     */   private int beatArtistAdv;
/*     */   private int beatExplDatAnniv;
/*     */   private int beatFAskDrink;
/*     */   private int beatRockyMarriage;
/*     */   private int beatRockyMarriage_WorkTable;
/*     */   private int beatPhoneCall;
/*     */   private boolean bGGreetsP;
/*     */   private boolean bAA_decorating_txnIn;
/*     */   private boolean bAA_decorating_txnOut;
/*     */   private boolean bAA_decorating_styleApt;
/*     */   private boolean bAA_decorating_couch;
/*     */   private boolean bAA_decorating_armoire;
/*     */   private boolean bAA_decorating_trinkets;
/*     */   private boolean bAA_decorating_paintings;
/*     */   private boolean bAA_decorating_weddingPicture;
/*     */   private boolean bAA_decorating_view;
/*     */   private boolean bAA_decorating_sideTable;
/*     */   private boolean bAA_decorating_rug;
/*     */   private boolean bExplDatAnniv;
/*     */   private boolean bRM_Italy;
/*     */   private boolean bFAskDrinks;
/*     */   private boolean bPhoneCall;
/*     */   
/*     */   public PostBeatMixinInfoWME()
/*     */   {
/*  39 */     this.beatGGreetsP = -1;
/*  40 */     this.beatArtistAdv = -1;
/*  41 */     this.beatExplDatAnniv = -1;
/*  42 */     this.beatFAskDrink = -1;
/*  43 */     this.beatRockyMarriage = -1;
/*  44 */     this.beatRockyMarriage_WorkTable = -1;
/*  45 */     this.beatPhoneCall = -1;
/*     */     
/*  47 */     this.bGGreetsP = false;
/*  48 */     this.bAA_decorating_txnIn = false;
/*  49 */     this.bAA_decorating_txnOut = false;
/*  50 */     this.bAA_decorating_styleApt = false;
/*  51 */     this.bAA_decorating_couch = false;
/*  52 */     this.bAA_decorating_armoire = false;
/*  53 */     this.bAA_decorating_trinkets = false;
/*  54 */     this.bAA_decorating_paintings = false;
/*  55 */     this.bAA_decorating_weddingPicture = false;
/*  56 */     this.bAA_decorating_view = false;
/*  57 */     this.bAA_decorating_sideTable = false;
/*  58 */     this.bAA_decorating_rug = false;
/*  59 */     this.bExplDatAnniv = false;
/*  60 */     this.bRM_Italy = false;
/*  61 */     this.bFAskDrinks = false;
/*  62 */     this.bPhoneCall = false;
/*     */   }
/*     */   
/*     */   public synchronized int getBeatGGreetsP() {
/*  66 */     return this.beatGGreetsP;
/*     */   }
/*     */   
/*     */ 
/*     */ 
/*     */ 
/*     */ 
/*     */ 
/*     */ 
/*     */ 
/*     */   public synchronized int getBeatArtistAdv()
/*     */   {
/*  78 */     return this.beatArtistAdv;
/*     */   }
/*     */   
/*     */ 
/*     */ 
/*     */ 
/*     */ 
/*     */ 
/*     */ 
/*     */ 
/*     */   public synchronized int getBeatExplDatAnniv()
/*     */   {
/*  90 */     return this.beatExplDatAnniv;
/*     */   }
/*     */   
/*     */ 
/*     */ 
/*     */ 
/*     */ 
/*     */ 
/*     */ 
/*     */ 
/*     */   public synchronized int getBeatFAskDrink()
/*     */   {
/* 102 */     return this.beatFAskDrink;
/*     */   }
/*     */   
/*     */ 
/*     */ 
/*     */ 
/*     */ 
/*     */ 
/*     */ 
/*     */ 
/*     */   public synchronized int getBeatRockyMarriage()
/*     */   {
/* 114 */     return this.beatRockyMarriage;
/*     */   }
/*     */   
/*     */ 
/*     */ 
/*     */ 
/*     */ 
/*     */ 
/*     */ 
/*     */ 
/*     */   public synchronized int getBeatRockyMarriage_WorkTable()
/*     */   {
/* 126 */     return this.beatRockyMarriage_WorkTable;
/*     */   }
/*     */   
/*     */ 
/*     */ 
/*     */ 
/*     */ 
/*     */ 
/*     */ 
/*     */ 
/*     */   public synchronized int getBeatPhoneCall()
/*     */   {
/* 138 */     return this.beatPhoneCall;
/*     */   }
/*     */   
/*     */ 
/*     */ 
/*     */ 
/*     */ 
/*     */ 
/*     */ 
/*     */ 
/*     */ 
/*     */ 
/*     */ 
/* 151 */   public synchronized boolean getBGGreetsP() { return this.bGGreetsP; }
/* 152 */   public synchronized boolean getbGGreetsP() { return this.bGGreetsP; }
/*     */   
/*     */ 
/*     */ 
/*     */ 
/*     */ 
/*     */ 
/*     */ 
/*     */ 
/*     */ 
/*     */ 
/*     */ 
/*     */ 
/*     */ 
/* 166 */   public synchronized boolean getBAA_decorating_txnIn() { return this.bAA_decorating_txnIn; }
/* 167 */   public synchronized boolean getbAA_decorating_txnIn() { return this.bAA_decorating_txnIn; }
/*     */   
/*     */ 
/*     */ 
/*     */ 
/*     */ 
/*     */ 
/*     */ 
/*     */ 
/*     */ 
/*     */ 
/*     */ 
/*     */ 
/*     */ 
/* 181 */   public synchronized boolean getBAA_decorating_txnOut() { return this.bAA_decorating_txnOut; }
/* 182 */   public synchronized boolean getbAA_decorating_txnOut() { return this.bAA_decorating_txnOut; }
/*     */   
/*     */ 
/*     */ 
/*     */ 
/*     */ 
/*     */ 
/*     */ 
/*     */ 
/*     */ 
/*     */ 
/*     */ 
/*     */ 
/* 195 */   public synchronized boolean getBAA_decorating_styleApt() { return this.bAA_decorating_styleApt; }
/* 196 */   public synchronized boolean getbAA_decorating_styleApt() { return this.bAA_decorating_styleApt; }
/*     */   
/*     */ 
/*     */ 
/*     */ 
/*     */ 
/*     */ 
/*     */ 
/*     */ 
/*     */ 
/*     */ 
/*     */ 
/*     */ 
/* 209 */   public synchronized boolean getBAA_decorating_couch() { return this.bAA_decorating_couch; }
/* 210 */   public synchronized boolean getbAA_decorating_couch() { return this.bAA_decorating_couch; }
/*     */   
/*     */ 
/*     */ 
/*     */ 
/*     */ 
/*     */ 
/*     */ 
/*     */ 
/*     */ 
/*     */ 
/*     */ 
/*     */ 
/* 223 */   public synchronized boolean getBAA_decorating_armoire() { return this.bAA_decorating_armoire; }
/* 224 */   public synchronized boolean getbAA_decorating_armoire() { return this.bAA_decorating_armoire; }
/*     */   
/*     */ 
/*     */ 
/*     */ 
/*     */ 
/*     */ 
/*     */ 
/*     */ 
/*     */ 
/*     */ 
/*     */ 
/*     */ 
/* 237 */   public synchronized boolean getBAA_decorating_trinkets() { return this.bAA_decorating_trinkets; }
/* 238 */   public synchronized boolean getbAA_decorating_trinkets() { return this.bAA_decorating_trinkets; }
/*     */   
/*     */ 
/*     */ 
/*     */ 
/*     */ 
/*     */ 
/*     */ 
/*     */ 
/*     */ 
/*     */ 
/*     */ 
/*     */ 
/* 251 */   public synchronized boolean getBAA_decorating_paintings() { return this.bAA_decorating_paintings; }
/* 252 */   public synchronized boolean getbAA_decorating_paintings() { return this.bAA_decorating_paintings; }
/*     */   
/*     */ 
/*     */ 
/*     */ 
/*     */ 
/*     */ 
/*     */ 
/*     */ 
/*     */ 
/*     */ 
/*     */ 
/*     */ 
/* 265 */   public synchronized boolean getBAA_decorating_weddingPicture() { return this.bAA_decorating_weddingPicture; }
/* 266 */   public synchronized boolean getbAA_decorating_weddingPicture() { return this.bAA_decorating_weddingPicture; }
/*     */   
/*     */ 
/*     */ 
/*     */ 
/*     */ 
/*     */ 
/*     */ 
/*     */ 
/*     */ 
/*     */ 
/*     */ 
/* 278 */   public synchronized boolean getBAA_decorating_view() { return this.bAA_decorating_view; }
/* 279 */   public synchronized boolean getbAA_decorating_view() { return this.bAA_decorating_view; }
/*     */   
/*     */ 
/*     */ 
/*     */ 
/*     */ 
/*     */ 
/*     */ 
/*     */ 
/*     */ 
/*     */ 
/*     */ 
/* 291 */   public synchronized boolean getBAA_decorating_sideTable() { return this.bAA_decorating_sideTable; }
/* 292 */   public synchronized boolean getbAA_decorating_sideTable() { return this.bAA_decorating_sideTable; }
/*     */   
/*     */ 
/*     */ 
/*     */ 
/*     */ 
/*     */ 
/*     */ 
/*     */ 
/*     */ 
/*     */ 
/*     */ 
/* 304 */   public synchronized boolean getBAA_decorating_rug() { return this.bAA_decorating_rug; }
/* 305 */   public synchronized boolean getbAA_decorating_rug() { return this.bAA_decorating_rug; }
/*     */   
/*     */ 
/*     */ 
/*     */ 
/*     */ 
/*     */ 
/*     */ 
/*     */ 
/*     */ 
/*     */ 
/*     */ 
/* 317 */   public synchronized boolean getBExplDatAnniv() { return this.bExplDatAnniv; }
/* 318 */   public synchronized boolean getbExplDatAnniv() { return this.bExplDatAnniv; }
/*     */   
/*     */ 
/*     */ 
/*     */ 
/*     */ 
/*     */ 
/*     */ 
/*     */ 
/*     */ 
/*     */ 
/*     */ 
/*     */ 
/*     */ 
/* 332 */   public synchronized boolean getBRM_Italy() { return this.bRM_Italy; }
/* 333 */   public synchronized boolean getbRM_Italy() { return this.bRM_Italy; }
/*     */   
/*     */ 
/*     */ 
/*     */ 
/*     */ 
/*     */ 
/*     */ 
/*     */ 
/*     */ 
/*     */ 
/*     */ 
/*     */ 
/* 346 */   public synchronized boolean getBFAskDrinks() { return this.bFAskDrinks; }
/* 347 */   public synchronized boolean getbFAskDrinks() { return this.bFAskDrinks; }
/*     */   
/*     */ 
/*     */ 
/*     */ 
/*     */ 
/*     */ 
/*     */ 
/*     */ 
/*     */ 
/*     */ 
/*     */ 
/*     */ 
/*     */ 
/* 361 */   public synchronized boolean getBPhoneCall() { return this.bPhoneCall; }
/* 362 */   public synchronized boolean getbPhoneCall() { return this.bPhoneCall; }
/*     */   
/*     */   /* Error */
/*     */   public void setBeatGGreetsP(int paramInt)
/*     */   {
/*     */     // Byte code:
/*     */     //   0: goto +6 -> 6
/*     */     //   3: aload_3
/*     */     //   4: monitorexit
/*     */     //   5: athrow
/*     */     //   6: aload_0
/*     */     //   7: dup
/*     */     //   8: astore_3
/*     */     //   9: monitorenter
/*     */     //   10: aload_0
/*     */     //   11: getfield 35	facade/characters/wmedef/PostBeatMixinInfoWME:beatGGreetsP	I
/*     */     //   14: istore_2
/*     */     //   15: aload_0
/*     */     //   16: iload_1
/*     */     //   17: putfield 35	facade/characters/wmedef/PostBeatMixinInfoWME:beatGGreetsP	I
/*     */     //   20: aload_3
/*     */     //   21: monitorexit
/*     */     //   22: aload_0
/*     */     //   23: getfield 41	facade/characters/wmedef/PostBeatMixinInfoWME:__support	Ljava/beans/PropertyChangeSupport;
/*     */     //   26: ldc 42
/*     */     //   28: iload_2
/*     */     //   29: iload_1
/*     */     //   30: invokevirtual 46	java/beans/PropertyChangeSupport:firePropertyChange	(Ljava/lang/String;II)V
/*     */     //   33: return
/*     */     // Line number table:
/*     */     //   Java source line #69	-> byte code offset #0
/*     */     //   Java source line #70	-> byte code offset #0
/*     */     //   Java source line #71	-> byte code offset #10
/*     */     //   Java source line #72	-> byte code offset #15
/*     */     //   Java source line #74	-> byte code offset #22
/*     */     //   Java source line #75	-> byte code offset #33
/*     */     // Local variable table:
/*     */     //   start	length	slot	name	signature
/*     */     //   0	34	0	this	PostBeatMixinInfoWME
/*     */     //   0	34	1	paramInt	int
/*     */     //   14	15	2	i	int
/*     */     //   3	18	3	Ljava/lang/Object;	Object
/*     */     // Exception table:
/*     */     //   from	to	target	type
/*     */     //   3	5	3	finally
/*     */     //   10	22	3	finally
/*     */   }
/*     */   
/*     */   /* Error */
/*     */   public void setBeatArtistAdv(int paramInt)
/*     */   {
/*     */     // Byte code:
/*     */     //   0: goto +6 -> 6
/*     */     //   3: aload_3
/*     */     //   4: monitorexit
/*     */     //   5: athrow
/*     */     //   6: aload_0
/*     */     //   7: dup
/*     */     //   8: astore_3
/*     */     //   9: monitorenter
/*     */     //   10: aload_0
/*     */     //   11: getfield 51	facade/characters/wmedef/PostBeatMixinInfoWME:beatArtistAdv	I
/*     */     //   14: istore_2
/*     */     //   15: aload_0
/*     */     //   16: iload_1
/*     */     //   17: putfield 51	facade/characters/wmedef/PostBeatMixinInfoWME:beatArtistAdv	I
/*     */     //   20: aload_3
/*     */     //   21: monitorexit
/*     */     //   22: aload_0
/*     */     //   23: getfield 41	facade/characters/wmedef/PostBeatMixinInfoWME:__support	Ljava/beans/PropertyChangeSupport;
/*     */     //   26: ldc 53
/*     */     //   28: iload_2
/*     */     //   29: iload_1
/*     */     //   30: invokevirtual 46	java/beans/PropertyChangeSupport:firePropertyChange	(Ljava/lang/String;II)V
/*     */     //   33: return
/*     */     // Line number table:
/*     */     //   Java source line #81	-> byte code offset #0
/*     */     //   Java source line #82	-> byte code offset #0
/*     */     //   Java source line #83	-> byte code offset #10
/*     */     //   Java source line #84	-> byte code offset #15
/*     */     //   Java source line #86	-> byte code offset #22
/*     */     //   Java source line #87	-> byte code offset #33
/*     */     // Local variable table:
/*     */     //   start	length	slot	name	signature
/*     */     //   0	34	0	this	PostBeatMixinInfoWME
/*     */     //   0	34	1	paramInt	int
/*     */     //   14	15	2	i	int
/*     */     //   3	18	3	Ljava/lang/Object;	Object
/*     */     // Exception table:
/*     */     //   from	to	target	type
/*     */     //   3	5	3	finally
/*     */     //   10	22	3	finally
/*     */   }
/*     */   
/*     */   /* Error */
/*     */   public void setBeatExplDatAnniv(int paramInt)
/*     */   {
/*     */     // Byte code:
/*     */     //   0: goto +6 -> 6
/*     */     //   3: aload_3
/*     */     //   4: monitorexit
/*     */     //   5: athrow
/*     */     //   6: aload_0
/*     */     //   7: dup
/*     */     //   8: astore_3
/*     */     //   9: monitorenter
/*     */     //   10: aload_0
/*     */     //   11: getfield 56	facade/characters/wmedef/PostBeatMixinInfoWME:beatExplDatAnniv	I
/*     */     //   14: istore_2
/*     */     //   15: aload_0
/*     */     //   16: iload_1
/*     */     //   17: putfield 56	facade/characters/wmedef/PostBeatMixinInfoWME:beatExplDatAnniv	I
/*     */     //   20: aload_3
/*     */     //   21: monitorexit
/*     */     //   22: aload_0
/*     */     //   23: getfield 41	facade/characters/wmedef/PostBeatMixinInfoWME:__support	Ljava/beans/PropertyChangeSupport;
/*     */     //   26: ldc 58
/*     */     //   28: iload_2
/*     */     //   29: iload_1
/*     */     //   30: invokevirtual 46	java/beans/PropertyChangeSupport:firePropertyChange	(Ljava/lang/String;II)V
/*     */     //   33: return
/*     */     // Line number table:
/*     */     //   Java source line #93	-> byte code offset #0
/*     */     //   Java source line #94	-> byte code offset #0
/*     */     //   Java source line #95	-> byte code offset #10
/*     */     //   Java source line #96	-> byte code offset #15
/*     */     //   Java source line #98	-> byte code offset #22
/*     */     //   Java source line #99	-> byte code offset #33
/*     */     // Local variable table:
/*     */     //   start	length	slot	name	signature
/*     */     //   0	34	0	this	PostBeatMixinInfoWME
/*     */     //   0	34	1	paramInt	int
/*     */     //   14	15	2	i	int
/*     */     //   3	18	3	Ljava/lang/Object;	Object
/*     */     // Exception table:
/*     */     //   from	to	target	type
/*     */     //   3	5	3	finally
/*     */     //   10	22	3	finally
/*     */   }
/*     */   
/*     */   /* Error */
/*     */   public void setBeatFAskDrink(int paramInt)
/*     */   {
/*     */     // Byte code:
/*     */     //   0: goto +6 -> 6
/*     */     //   3: aload_3
/*     */     //   4: monitorexit
/*     */     //   5: athrow
/*     */     //   6: aload_0
/*     */     //   7: dup
/*     */     //   8: astore_3
/*     */     //   9: monitorenter
/*     */     //   10: aload_0
/*     */     //   11: getfield 61	facade/characters/wmedef/PostBeatMixinInfoWME:beatFAskDrink	I
/*     */     //   14: istore_2
/*     */     //   15: aload_0
/*     */     //   16: iload_1
/*     */     //   17: putfield 61	facade/characters/wmedef/PostBeatMixinInfoWME:beatFAskDrink	I
/*     */     //   20: aload_3
/*     */     //   21: monitorexit
/*     */     //   22: aload_0
/*     */     //   23: getfield 41	facade/characters/wmedef/PostBeatMixinInfoWME:__support	Ljava/beans/PropertyChangeSupport;
/*     */     //   26: ldc 63
/*     */     //   28: iload_2
/*     */     //   29: iload_1
/*     */     //   30: invokevirtual 46	java/beans/PropertyChangeSupport:firePropertyChange	(Ljava/lang/String;II)V
/*     */     //   33: return
/*     */     // Line number table:
/*     */     //   Java source line #105	-> byte code offset #0
/*     */     //   Java source line #106	-> byte code offset #0
/*     */     //   Java source line #107	-> byte code offset #10
/*     */     //   Java source line #108	-> byte code offset #15
/*     */     //   Java source line #110	-> byte code offset #22
/*     */     //   Java source line #111	-> byte code offset #33
/*     */     // Local variable table:
/*     */     //   start	length	slot	name	signature
/*     */     //   0	34	0	this	PostBeatMixinInfoWME
/*     */     //   0	34	1	paramInt	int
/*     */     //   14	15	2	i	int
/*     */     //   3	18	3	Ljava/lang/Object;	Object
/*     */     // Exception table:
/*     */     //   from	to	target	type
/*     */     //   3	5	3	finally
/*     */     //   10	22	3	finally
/*     */   }
/*     */   
/*     */   /* Error */
/*     */   public void setBeatRockyMarriage(int paramInt)
/*     */   {
/*     */     // Byte code:
/*     */     //   0: goto +6 -> 6
/*     */     //   3: aload_3
/*     */     //   4: monitorexit
/*     */     //   5: athrow
/*     */     //   6: aload_0
/*     */     //   7: dup
/*     */     //   8: astore_3
/*     */     //   9: monitorenter
/*     */     //   10: aload_0
/*     */     //   11: getfield 66	facade/characters/wmedef/PostBeatMixinInfoWME:beatRockyMarriage	I
/*     */     //   14: istore_2
/*     */     //   15: aload_0
/*     */     //   16: iload_1
/*     */     //   17: putfield 66	facade/characters/wmedef/PostBeatMixinInfoWME:beatRockyMarriage	I
/*     */     //   20: aload_3
/*     */     //   21: monitorexit
/*     */     //   22: aload_0
/*     */     //   23: getfield 41	facade/characters/wmedef/PostBeatMixinInfoWME:__support	Ljava/beans/PropertyChangeSupport;
/*     */     //   26: ldc 68
/*     */     //   28: iload_2
/*     */     //   29: iload_1
/*     */     //   30: invokevirtual 46	java/beans/PropertyChangeSupport:firePropertyChange	(Ljava/lang/String;II)V
/*     */     //   33: return
/*     */     // Line number table:
/*     */     //   Java source line #117	-> byte code offset #0
/*     */     //   Java source line #118	-> byte code offset #0
/*     */     //   Java source line #119	-> byte code offset #10
/*     */     //   Java source line #120	-> byte code offset #15
/*     */     //   Java source line #122	-> byte code offset #22
/*     */     //   Java source line #123	-> byte code offset #33
/*     */     // Local variable table:
/*     */     //   start	length	slot	name	signature
/*     */     //   0	34	0	this	PostBeatMixinInfoWME
/*     */     //   0	34	1	paramInt	int
/*     */     //   14	15	2	i	int
/*     */     //   3	18	3	Ljava/lang/Object;	Object
/*     */     // Exception table:
/*     */     //   from	to	target	type
/*     */     //   3	5	3	finally
/*     */     //   10	22	3	finally
/*     */   }
/*     */   
/*     */   /* Error */
/*     */   public void setBeatRockyMarriage_WorkTable(int paramInt)
/*     */   {
/*     */     // Byte code:
/*     */     //   0: goto +6 -> 6
/*     */     //   3: aload_3
/*     */     //   4: monitorexit
/*     */     //   5: athrow
/*     */     //   6: aload_0
/*     */     //   7: dup
/*     */     //   8: astore_3
/*     */     //   9: monitorenter
/*     */     //   10: aload_0
/*     */     //   11: getfield 71	facade/characters/wmedef/PostBeatMixinInfoWME:beatRockyMarriage_WorkTable	I
/*     */     //   14: istore_2
/*     */     //   15: aload_0
/*     */     //   16: iload_1
/*     */     //   17: putfield 71	facade/characters/wmedef/PostBeatMixinInfoWME:beatRockyMarriage_WorkTable	I
/*     */     //   20: aload_3
/*     */     //   21: monitorexit
/*     */     //   22: aload_0
/*     */     //   23: getfield 41	facade/characters/wmedef/PostBeatMixinInfoWME:__support	Ljava/beans/PropertyChangeSupport;
/*     */     //   26: ldc 73
/*     */     //   28: iload_2
/*     */     //   29: iload_1
/*     */     //   30: invokevirtual 46	java/beans/PropertyChangeSupport:firePropertyChange	(Ljava/lang/String;II)V
/*     */     //   33: return
/*     */     // Line number table:
/*     */     //   Java source line #129	-> byte code offset #0
/*     */     //   Java source line #130	-> byte code offset #0
/*     */     //   Java source line #131	-> byte code offset #10
/*     */     //   Java source line #132	-> byte code offset #15
/*     */     //   Java source line #134	-> byte code offset #22
/*     */     //   Java source line #135	-> byte code offset #33
/*     */     // Local variable table:
/*     */     //   start	length	slot	name	signature
/*     */     //   0	34	0	this	PostBeatMixinInfoWME
/*     */     //   0	34	1	paramInt	int
/*     */     //   14	15	2	i	int
/*     */     //   3	18	3	Ljava/lang/Object;	Object
/*     */     // Exception table:
/*     */     //   from	to	target	type
/*     */     //   3	5	3	finally
/*     */     //   10	22	3	finally
/*     */   }
/*     */   
/*     */   /* Error */
/*     */   public void setBeatPhoneCall(int paramInt)
/*     */   {
/*     */     // Byte code:
/*     */     //   0: goto +6 -> 6
/*     */     //   3: aload_3
/*     */     //   4: monitorexit
/*     */     //   5: athrow
/*     */     //   6: aload_0
/*     */     //   7: dup
/*     */     //   8: astore_3
/*     */     //   9: monitorenter
/*     */     //   10: aload_0
/*     */     //   11: getfield 76	facade/characters/wmedef/PostBeatMixinInfoWME:beatPhoneCall	I
/*     */     //   14: istore_2
/*     */     //   15: aload_0
/*     */     //   16: iload_1
/*     */     //   17: putfield 76	facade/characters/wmedef/PostBeatMixinInfoWME:beatPhoneCall	I
/*     */     //   20: aload_3
/*     */     //   21: monitorexit
/*     */     //   22: aload_0
/*     */     //   23: getfield 41	facade/characters/wmedef/PostBeatMixinInfoWME:__support	Ljava/beans/PropertyChangeSupport;
/*     */     //   26: ldc 78
/*     */     //   28: iload_2
/*     */     //   29: iload_1
/*     */     //   30: invokevirtual 46	java/beans/PropertyChangeSupport:firePropertyChange	(Ljava/lang/String;II)V
/*     */     //   33: return
/*     */     // Line number table:
/*     */     //   Java source line #141	-> byte code offset #0
/*     */     //   Java source line #142	-> byte code offset #0
/*     */     //   Java source line #143	-> byte code offset #10
/*     */     //   Java source line #144	-> byte code offset #15
/*     */     //   Java source line #146	-> byte code offset #22
/*     */     //   Java source line #147	-> byte code offset #33
/*     */     // Local variable table:
/*     */     //   start	length	slot	name	signature
/*     */     //   0	34	0	this	PostBeatMixinInfoWME
/*     */     //   0	34	1	paramInt	int
/*     */     //   14	15	2	i	int
/*     */     //   3	18	3	Ljava/lang/Object;	Object
/*     */     // Exception table:
/*     */     //   from	to	target	type
/*     */     //   3	5	3	finally
/*     */     //   10	22	3	finally
/*     */   }
/*     */   
/*     */   /* Error */
/*     */   public void setBGGreetsP(boolean paramBoolean)
/*     */   {
/*     */     // Byte code:
/*     */     //   0: goto +6 -> 6
/*     */     //   3: aload_3
/*     */     //   4: monitorexit
/*     */     //   5: athrow
/*     */     //   6: aload_0
/*     */     //   7: dup
/*     */     //   8: astore_3
/*     */     //   9: monitorenter
/*     */     //   10: aload_0
/*     */     //   11: getfield 82	facade/characters/wmedef/PostBeatMixinInfoWME:bGGreetsP	Z
/*     */     //   14: istore_2
/*     */     //   15: aload_0
/*     */     //   16: iload_1
/*     */     //   17: putfield 82	facade/characters/wmedef/PostBeatMixinInfoWME:bGGreetsP	Z
/*     */     //   20: aload_3
/*     */     //   21: monitorexit
/*     */     //   22: aload_0
/*     */     //   23: getfield 41	facade/characters/wmedef/PostBeatMixinInfoWME:__support	Ljava/beans/PropertyChangeSupport;
/*     */     //   26: ldc 86
/*     */     //   28: iload_2
/*     */     //   29: iload_1
/*     */     //   30: invokevirtual 89	java/beans/PropertyChangeSupport:firePropertyChange	(Ljava/lang/String;ZZ)V
/*     */     //   33: return
/*     */     // Line number table:
/*     */     //   Java source line #155	-> byte code offset #0
/*     */     //   Java source line #156	-> byte code offset #0
/*     */     //   Java source line #157	-> byte code offset #10
/*     */     //   Java source line #158	-> byte code offset #15
/*     */     //   Java source line #160	-> byte code offset #22
/*     */     //   Java source line #161	-> byte code offset #33
/*     */     // Local variable table:
/*     */     //   start	length	slot	name	signature
/*     */     //   0	34	0	this	PostBeatMixinInfoWME
/*     */     //   0	34	1	paramBoolean	boolean
/*     */     //   14	15	2	bool	boolean
/*     */     //   3	18	3	Ljava/lang/Object;	Object
/*     */     // Exception table:
/*     */     //   from	to	target	type
/*     */     //   3	5	3	finally
/*     */     //   10	22	3	finally
/*     */   }
/*     */   
/*     */   /* Error */
/*     */   public void setBAA_decorating_txnIn(boolean paramBoolean)
/*     */   {
/*     */     // Byte code:
/*     */     //   0: goto +6 -> 6
/*     */     //   3: aload_3
/*     */     //   4: monitorexit
/*     */     //   5: athrow
/*     */     //   6: aload_0
/*     */     //   7: dup
/*     */     //   8: astore_3
/*     */     //   9: monitorenter
/*     */     //   10: aload_0
/*     */     //   11: getfield 92	facade/characters/wmedef/PostBeatMixinInfoWME:bAA_decorating_txnIn	Z
/*     */     //   14: istore_2
/*     */     //   15: aload_0
/*     */     //   16: iload_1
/*     */     //   17: putfield 92	facade/characters/wmedef/PostBeatMixinInfoWME:bAA_decorating_txnIn	Z
/*     */     //   20: aload_3
/*     */     //   21: monitorexit
/*     */     //   22: aload_0
/*     */     //   23: getfield 41	facade/characters/wmedef/PostBeatMixinInfoWME:__support	Ljava/beans/PropertyChangeSupport;
/*     */     //   26: ldc 95
/*     */     //   28: iload_2
/*     */     //   29: iload_1
/*     */     //   30: invokevirtual 89	java/beans/PropertyChangeSupport:firePropertyChange	(Ljava/lang/String;ZZ)V
/*     */     //   33: return
/*     */     // Line number table:
/*     */     //   Java source line #170	-> byte code offset #0
/*     */     //   Java source line #171	-> byte code offset #0
/*     */     //   Java source line #172	-> byte code offset #10
/*     */     //   Java source line #173	-> byte code offset #15
/*     */     //   Java source line #175	-> byte code offset #22
/*     */     //   Java source line #176	-> byte code offset #33
/*     */     // Local variable table:
/*     */     //   start	length	slot	name	signature
/*     */     //   0	34	0	this	PostBeatMixinInfoWME
/*     */     //   0	34	1	paramBoolean	boolean
/*     */     //   14	15	2	bool	boolean
/*     */     //   3	18	3	Ljava/lang/Object;	Object
/*     */     // Exception table:
/*     */     //   from	to	target	type
/*     */     //   3	5	3	finally
/*     */     //   10	22	3	finally
/*     */   }
/*     */   
/*     */   /* Error */
/*     */   public void setBAA_decorating_txnOut(boolean paramBoolean)
/*     */   {
/*     */     // Byte code:
/*     */     //   0: goto +6 -> 6
/*     */     //   3: aload_3
/*     */     //   4: monitorexit
/*     */     //   5: athrow
/*     */     //   6: aload_0
/*     */     //   7: dup
/*     */     //   8: astore_3
/*     */     //   9: monitorenter
/*     */     //   10: aload_0
/*     */     //   11: getfield 98	facade/characters/wmedef/PostBeatMixinInfoWME:bAA_decorating_txnOut	Z
/*     */     //   14: istore_2
/*     */     //   15: aload_0
/*     */     //   16: iload_1
/*     */     //   17: putfield 98	facade/characters/wmedef/PostBeatMixinInfoWME:bAA_decorating_txnOut	Z
/*     */     //   20: aload_3
/*     */     //   21: monitorexit
/*     */     //   22: aload_0
/*     */     //   23: getfield 41	facade/characters/wmedef/PostBeatMixinInfoWME:__support	Ljava/beans/PropertyChangeSupport;
/*     */     //   26: ldc 101
/*     */     //   28: iload_2
/*     */     //   29: iload_1
/*     */     //   30: invokevirtual 89	java/beans/PropertyChangeSupport:firePropertyChange	(Ljava/lang/String;ZZ)V
/*     */     //   33: return
/*     */     // Line number table:
/*     */     //   Java source line #185	-> byte code offset #0
/*     */     //   Java source line #186	-> byte code offset #0
/*     */     //   Java source line #187	-> byte code offset #10
/*     */     //   Java source line #188	-> byte code offset #15
/*     */     //   Java source line #190	-> byte code offset #22
/*     */     //   Java source line #191	-> byte code offset #33
/*     */     // Local variable table:
/*     */     //   start	length	slot	name	signature
/*     */     //   0	34	0	this	PostBeatMixinInfoWME
/*     */     //   0	34	1	paramBoolean	boolean
/*     */     //   14	15	2	bool	boolean
/*     */     //   3	18	3	Ljava/lang/Object;	Object
/*     */     // Exception table:
/*     */     //   from	to	target	type
/*     */     //   3	5	3	finally
/*     */     //   10	22	3	finally
/*     */   }
/*     */   
/*     */   /* Error */
/*     */   public void setBAA_decorating_styleApt(boolean paramBoolean)
/*     */   {
/*     */     // Byte code:
/*     */     //   0: goto +6 -> 6
/*     */     //   3: aload_3
/*     */     //   4: monitorexit
/*     */     //   5: athrow
/*     */     //   6: aload_0
/*     */     //   7: dup
/*     */     //   8: astore_3
/*     */     //   9: monitorenter
/*     */     //   10: aload_0
/*     */     //   11: getfield 104	facade/characters/wmedef/PostBeatMixinInfoWME:bAA_decorating_styleApt	Z
/*     */     //   14: istore_2
/*     */     //   15: aload_0
/*     */     //   16: iload_1
/*     */     //   17: putfield 104	facade/characters/wmedef/PostBeatMixinInfoWME:bAA_decorating_styleApt	Z
/*     */     //   20: aload_3
/*     */     //   21: monitorexit
/*     */     //   22: aload_0
/*     */     //   23: getfield 41	facade/characters/wmedef/PostBeatMixinInfoWME:__support	Ljava/beans/PropertyChangeSupport;
/*     */     //   26: ldc 107
/*     */     //   28: iload_2
/*     */     //   29: iload_1
/*     */     //   30: invokevirtual 89	java/beans/PropertyChangeSupport:firePropertyChange	(Ljava/lang/String;ZZ)V
/*     */     //   33: return
/*     */     // Line number table:
/*     */     //   Java source line #199	-> byte code offset #0
/*     */     //   Java source line #200	-> byte code offset #0
/*     */     //   Java source line #201	-> byte code offset #10
/*     */     //   Java source line #202	-> byte code offset #15
/*     */     //   Java source line #204	-> byte code offset #22
/*     */     //   Java source line #205	-> byte code offset #33
/*     */     // Local variable table:
/*     */     //   start	length	slot	name	signature
/*     */     //   0	34	0	this	PostBeatMixinInfoWME
/*     */     //   0	34	1	paramBoolean	boolean
/*     */     //   14	15	2	bool	boolean
/*     */     //   3	18	3	Ljava/lang/Object;	Object
/*     */     // Exception table:
/*     */     //   from	to	target	type
/*     */     //   3	5	3	finally
/*     */     //   10	22	3	finally
/*     */   }
/*     */   
/*     */   /* Error */
/*     */   public void setBAA_decorating_couch(boolean paramBoolean)
/*     */   {
/*     */     // Byte code:
/*     */     //   0: goto +6 -> 6
/*     */     //   3: aload_3
/*     */     //   4: monitorexit
/*     */     //   5: athrow
/*     */     //   6: aload_0
/*     */     //   7: dup
/*     */     //   8: astore_3
/*     */     //   9: monitorenter
/*     */     //   10: aload_0
/*     */     //   11: getfield 110	facade/characters/wmedef/PostBeatMixinInfoWME:bAA_decorating_couch	Z
/*     */     //   14: istore_2
/*     */     //   15: aload_0
/*     */     //   16: iload_1
/*     */     //   17: putfield 110	facade/characters/wmedef/PostBeatMixinInfoWME:bAA_decorating_couch	Z
/*     */     //   20: aload_3
/*     */     //   21: monitorexit
/*     */     //   22: aload_0
/*     */     //   23: getfield 41	facade/characters/wmedef/PostBeatMixinInfoWME:__support	Ljava/beans/PropertyChangeSupport;
/*     */     //   26: ldc 113
/*     */     //   28: iload_2
/*     */     //   29: iload_1
/*     */     //   30: invokevirtual 89	java/beans/PropertyChangeSupport:firePropertyChange	(Ljava/lang/String;ZZ)V
/*     */     //   33: return
/*     */     // Line number table:
/*     */     //   Java source line #213	-> byte code offset #0
/*     */     //   Java source line #214	-> byte code offset #0
/*     */     //   Java source line #215	-> byte code offset #10
/*     */     //   Java source line #216	-> byte code offset #15
/*     */     //   Java source line #218	-> byte code offset #22
/*     */     //   Java source line #219	-> byte code offset #33
/*     */     // Local variable table:
/*     */     //   start	length	slot	name	signature
/*     */     //   0	34	0	this	PostBeatMixinInfoWME
/*     */     //   0	34	1	paramBoolean	boolean
/*     */     //   14	15	2	bool	boolean
/*     */     //   3	18	3	Ljava/lang/Object;	Object
/*     */     // Exception table:
/*     */     //   from	to	target	type
/*     */     //   3	5	3	finally
/*     */     //   10	22	3	finally
/*     */   }
/*     */   
/*     */   /* Error */
/*     */   public void setBAA_decorating_armoire(boolean paramBoolean)
/*     */   {
/*     */     // Byte code:
/*     */     //   0: goto +6 -> 6
/*     */     //   3: aload_3
/*     */     //   4: monitorexit
/*     */     //   5: athrow
/*     */     //   6: aload_0
/*     */     //   7: dup
/*     */     //   8: astore_3
/*     */     //   9: monitorenter
/*     */     //   10: aload_0
/*     */     //   11: getfield 116	facade/characters/wmedef/PostBeatMixinInfoWME:bAA_decorating_armoire	Z
/*     */     //   14: istore_2
/*     */     //   15: aload_0
/*     */     //   16: iload_1
/*     */     //   17: putfield 116	facade/characters/wmedef/PostBeatMixinInfoWME:bAA_decorating_armoire	Z
/*     */     //   20: aload_3
/*     */     //   21: monitorexit
/*     */     //   22: aload_0
/*     */     //   23: getfield 41	facade/characters/wmedef/PostBeatMixinInfoWME:__support	Ljava/beans/PropertyChangeSupport;
/*     */     //   26: ldc 119
/*     */     //   28: iload_2
/*     */     //   29: iload_1
/*     */     //   30: invokevirtual 89	java/beans/PropertyChangeSupport:firePropertyChange	(Ljava/lang/String;ZZ)V
/*     */     //   33: return
/*     */     // Line number table:
/*     */     //   Java source line #227	-> byte code offset #0
/*     */     //   Java source line #228	-> byte code offset #0
/*     */     //   Java source line #229	-> byte code offset #10
/*     */     //   Java source line #230	-> byte code offset #15
/*     */     //   Java source line #232	-> byte code offset #22
/*     */     //   Java source line #233	-> byte code offset #33
/*     */     // Local variable table:
/*     */     //   start	length	slot	name	signature
/*     */     //   0	34	0	this	PostBeatMixinInfoWME
/*     */     //   0	34	1	paramBoolean	boolean
/*     */     //   14	15	2	bool	boolean
/*     */     //   3	18	3	Ljava/lang/Object;	Object
/*     */     // Exception table:
/*     */     //   from	to	target	type
/*     */     //   3	5	3	finally
/*     */     //   10	22	3	finally
/*     */   }
/*     */   
/*     */   /* Error */
/*     */   public void setBAA_decorating_trinkets(boolean paramBoolean)
/*     */   {
/*     */     // Byte code:
/*     */     //   0: goto +6 -> 6
/*     */     //   3: aload_3
/*     */     //   4: monitorexit
/*     */     //   5: athrow
/*     */     //   6: aload_0
/*     */     //   7: dup
/*     */     //   8: astore_3
/*     */     //   9: monitorenter
/*     */     //   10: aload_0
/*     */     //   11: getfield 122	facade/characters/wmedef/PostBeatMixinInfoWME:bAA_decorating_trinkets	Z
/*     */     //   14: istore_2
/*     */     //   15: aload_0
/*     */     //   16: iload_1
/*     */     //   17: putfield 122	facade/characters/wmedef/PostBeatMixinInfoWME:bAA_decorating_trinkets	Z
/*     */     //   20: aload_3
/*     */     //   21: monitorexit
/*     */     //   22: aload_0
/*     */     //   23: getfield 41	facade/characters/wmedef/PostBeatMixinInfoWME:__support	Ljava/beans/PropertyChangeSupport;
/*     */     //   26: ldc 125
/*     */     //   28: iload_2
/*     */     //   29: iload_1
/*     */     //   30: invokevirtual 89	java/beans/PropertyChangeSupport:firePropertyChange	(Ljava/lang/String;ZZ)V
/*     */     //   33: return
/*     */     // Line number table:
/*     */     //   Java source line #241	-> byte code offset #0
/*     */     //   Java source line #242	-> byte code offset #0
/*     */     //   Java source line #243	-> byte code offset #10
/*     */     //   Java source line #244	-> byte code offset #15
/*     */     //   Java source line #246	-> byte code offset #22
/*     */     //   Java source line #247	-> byte code offset #33
/*     */     // Local variable table:
/*     */     //   start	length	slot	name	signature
/*     */     //   0	34	0	this	PostBeatMixinInfoWME
/*     */     //   0	34	1	paramBoolean	boolean
/*     */     //   14	15	2	bool	boolean
/*     */     //   3	18	3	Ljava/lang/Object;	Object
/*     */     // Exception table:
/*     */     //   from	to	target	type
/*     */     //   3	5	3	finally
/*     */     //   10	22	3	finally
/*     */   }
/*     */   
/*     */   /* Error */
/*     */   public void setBAA_decorating_paintings(boolean paramBoolean)
/*     */   {
/*     */     // Byte code:
/*     */     //   0: goto +6 -> 6
/*     */     //   3: aload_3
/*     */     //   4: monitorexit
/*     */     //   5: athrow
/*     */     //   6: aload_0
/*     */     //   7: dup
/*     */     //   8: astore_3
/*     */     //   9: monitorenter
/*     */     //   10: aload_0
/*     */     //   11: getfield 128	facade/characters/wmedef/PostBeatMixinInfoWME:bAA_decorating_paintings	Z
/*     */     //   14: istore_2
/*     */     //   15: aload_0
/*     */     //   16: iload_1
/*     */     //   17: putfield 128	facade/characters/wmedef/PostBeatMixinInfoWME:bAA_decorating_paintings	Z
/*     */     //   20: aload_3
/*     */     //   21: monitorexit
/*     */     //   22: aload_0
/*     */     //   23: getfield 41	facade/characters/wmedef/PostBeatMixinInfoWME:__support	Ljava/beans/PropertyChangeSupport;
/*     */     //   26: ldc -125
/*     */     //   28: iload_2
/*     */     //   29: iload_1
/*     */     //   30: invokevirtual 89	java/beans/PropertyChangeSupport:firePropertyChange	(Ljava/lang/String;ZZ)V
/*     */     //   33: return
/*     */     // Line number table:
/*     */     //   Java source line #255	-> byte code offset #0
/*     */     //   Java source line #256	-> byte code offset #0
/*     */     //   Java source line #257	-> byte code offset #10
/*     */     //   Java source line #258	-> byte code offset #15
/*     */     //   Java source line #260	-> byte code offset #22
/*     */     //   Java source line #261	-> byte code offset #33
/*     */     // Local variable table:
/*     */     //   start	length	slot	name	signature
/*     */     //   0	34	0	this	PostBeatMixinInfoWME
/*     */     //   0	34	1	paramBoolean	boolean
/*     */     //   14	15	2	bool	boolean
/*     */     //   3	18	3	Ljava/lang/Object;	Object
/*     */     // Exception table:
/*     */     //   from	to	target	type
/*     */     //   3	5	3	finally
/*     */     //   10	22	3	finally
/*     */   }
/*     */   
/*     */   /* Error */
/*     */   public void setBAA_decorating_weddingPicture(boolean paramBoolean)
/*     */   {
/*     */     // Byte code:
/*     */     //   0: goto +6 -> 6
/*     */     //   3: aload_3
/*     */     //   4: monitorexit
/*     */     //   5: athrow
/*     */     //   6: aload_0
/*     */     //   7: dup
/*     */     //   8: astore_3
/*     */     //   9: monitorenter
/*     */     //   10: aload_0
/*     */     //   11: getfield 134	facade/characters/wmedef/PostBeatMixinInfoWME:bAA_decorating_weddingPicture	Z
/*     */     //   14: istore_2
/*     */     //   15: aload_0
/*     */     //   16: iload_1
/*     */     //   17: putfield 134	facade/characters/wmedef/PostBeatMixinInfoWME:bAA_decorating_weddingPicture	Z
/*     */     //   20: aload_3
/*     */     //   21: monitorexit
/*     */     //   22: aload_0
/*     */     //   23: getfield 41	facade/characters/wmedef/PostBeatMixinInfoWME:__support	Ljava/beans/PropertyChangeSupport;
/*     */     //   26: ldc -119
/*     */     //   28: iload_2
/*     */     //   29: iload_1
/*     */     //   30: invokevirtual 89	java/beans/PropertyChangeSupport:firePropertyChange	(Ljava/lang/String;ZZ)V
/*     */     //   33: return
/*     */     // Line number table:
/*     */     //   Java source line #269	-> byte code offset #0
/*     */     //   Java source line #270	-> byte code offset #0
/*     */     //   Java source line #271	-> byte code offset #10
/*     */     //   Java source line #272	-> byte code offset #15
/*     */     //   Java source line #274	-> byte code offset #22
/*     */     //   Java source line #275	-> byte code offset #33
/*     */     // Local variable table:
/*     */     //   start	length	slot	name	signature
/*     */     //   0	34	0	this	PostBeatMixinInfoWME
/*     */     //   0	34	1	paramBoolean	boolean
/*     */     //   14	15	2	bool	boolean
/*     */     //   3	18	3	Ljava/lang/Object;	Object
/*     */     // Exception table:
/*     */     //   from	to	target	type
/*     */     //   3	5	3	finally
/*     */     //   10	22	3	finally
/*     */   }
/*     */   
/*     */   /* Error */
/*     */   public void setBAA_decorating_view(boolean paramBoolean)
/*     */   {
/*     */     // Byte code:
/*     */     //   0: goto +6 -> 6
/*     */     //   3: aload_3
/*     */     //   4: monitorexit
/*     */     //   5: athrow
/*     */     //   6: aload_0
/*     */     //   7: dup
/*     */     //   8: astore_3
/*     */     //   9: monitorenter
/*     */     //   10: aload_0
/*     */     //   11: getfield 140	facade/characters/wmedef/PostBeatMixinInfoWME:bAA_decorating_view	Z
/*     */     //   14: istore_2
/*     */     //   15: aload_0
/*     */     //   16: iload_1
/*     */     //   17: putfield 140	facade/characters/wmedef/PostBeatMixinInfoWME:bAA_decorating_view	Z
/*     */     //   20: aload_3
/*     */     //   21: monitorexit
/*     */     //   22: aload_0
/*     */     //   23: getfield 41	facade/characters/wmedef/PostBeatMixinInfoWME:__support	Ljava/beans/PropertyChangeSupport;
/*     */     //   26: ldc -113
/*     */     //   28: iload_2
/*     */     //   29: iload_1
/*     */     //   30: invokevirtual 89	java/beans/PropertyChangeSupport:firePropertyChange	(Ljava/lang/String;ZZ)V
/*     */     //   33: return
/*     */     // Line number table:
/*     */     //   Java source line #282	-> byte code offset #0
/*     */     //   Java source line #283	-> byte code offset #0
/*     */     //   Java source line #284	-> byte code offset #10
/*     */     //   Java source line #285	-> byte code offset #15
/*     */     //   Java source line #287	-> byte code offset #22
/*     */     //   Java source line #288	-> byte code offset #33
/*     */     // Local variable table:
/*     */     //   start	length	slot	name	signature
/*     */     //   0	34	0	this	PostBeatMixinInfoWME
/*     */     //   0	34	1	paramBoolean	boolean
/*     */     //   14	15	2	bool	boolean
/*     */     //   3	18	3	Ljava/lang/Object;	Object
/*     */     // Exception table:
/*     */     //   from	to	target	type
/*     */     //   3	5	3	finally
/*     */     //   10	22	3	finally
/*     */   }
/*     */   
/*     */   /* Error */
/*     */   public void setBAA_decorating_sideTable(boolean paramBoolean)
/*     */   {
/*     */     // Byte code:
/*     */     //   0: goto +6 -> 6
/*     */     //   3: aload_3
/*     */     //   4: monitorexit
/*     */     //   5: athrow
/*     */     //   6: aload_0
/*     */     //   7: dup
/*     */     //   8: astore_3
/*     */     //   9: monitorenter
/*     */     //   10: aload_0
/*     */     //   11: getfield 146	facade/characters/wmedef/PostBeatMixinInfoWME:bAA_decorating_sideTable	Z
/*     */     //   14: istore_2
/*     */     //   15: aload_0
/*     */     //   16: iload_1
/*     */     //   17: putfield 146	facade/characters/wmedef/PostBeatMixinInfoWME:bAA_decorating_sideTable	Z
/*     */     //   20: aload_3
/*     */     //   21: monitorexit
/*     */     //   22: aload_0
/*     */     //   23: getfield 41	facade/characters/wmedef/PostBeatMixinInfoWME:__support	Ljava/beans/PropertyChangeSupport;
/*     */     //   26: ldc -107
/*     */     //   28: iload_2
/*     */     //   29: iload_1
/*     */     //   30: invokevirtual 89	java/beans/PropertyChangeSupport:firePropertyChange	(Ljava/lang/String;ZZ)V
/*     */     //   33: return
/*     */     // Line number table:
/*     */     //   Java source line #295	-> byte code offset #0
/*     */     //   Java source line #296	-> byte code offset #0
/*     */     //   Java source line #297	-> byte code offset #10
/*     */     //   Java source line #298	-> byte code offset #15
/*     */     //   Java source line #300	-> byte code offset #22
/*     */     //   Java source line #301	-> byte code offset #33
/*     */     // Local variable table:
/*     */     //   start	length	slot	name	signature
/*     */     //   0	34	0	this	PostBeatMixinInfoWME
/*     */     //   0	34	1	paramBoolean	boolean
/*     */     //   14	15	2	bool	boolean
/*     */     //   3	18	3	Ljava/lang/Object;	Object
/*     */     // Exception table:
/*     */     //   from	to	target	type
/*     */     //   3	5	3	finally
/*     */     //   10	22	3	finally
/*     */   }
/*     */   
/*     */   /* Error */
/*     */   public void setBAA_decorating_rug(boolean paramBoolean)
/*     */   {
/*     */     // Byte code:
/*     */     //   0: goto +6 -> 6
/*     */     //   3: aload_3
/*     */     //   4: monitorexit
/*     */     //   5: athrow
/*     */     //   6: aload_0
/*     */     //   7: dup
/*     */     //   8: astore_3
/*     */     //   9: monitorenter
/*     */     //   10: aload_0
/*     */     //   11: getfield 152	facade/characters/wmedef/PostBeatMixinInfoWME:bAA_decorating_rug	Z
/*     */     //   14: istore_2
/*     */     //   15: aload_0
/*     */     //   16: iload_1
/*     */     //   17: putfield 152	facade/characters/wmedef/PostBeatMixinInfoWME:bAA_decorating_rug	Z
/*     */     //   20: aload_3
/*     */     //   21: monitorexit
/*     */     //   22: aload_0
/*     */     //   23: getfield 41	facade/characters/wmedef/PostBeatMixinInfoWME:__support	Ljava/beans/PropertyChangeSupport;
/*     */     //   26: ldc -101
/*     */     //   28: iload_2
/*     */     //   29: iload_1
/*     */     //   30: invokevirtual 89	java/beans/PropertyChangeSupport:firePropertyChange	(Ljava/lang/String;ZZ)V
/*     */     //   33: return
/*     */     // Line number table:
/*     */     //   Java source line #308	-> byte code offset #0
/*     */     //   Java source line #309	-> byte code offset #0
/*     */     //   Java source line #310	-> byte code offset #10
/*     */     //   Java source line #311	-> byte code offset #15
/*     */     //   Java source line #313	-> byte code offset #22
/*     */     //   Java source line #314	-> byte code offset #33
/*     */     // Local variable table:
/*     */     //   start	length	slot	name	signature
/*     */     //   0	34	0	this	PostBeatMixinInfoWME
/*     */     //   0	34	1	paramBoolean	boolean
/*     */     //   14	15	2	bool	boolean
/*     */     //   3	18	3	Ljava/lang/Object;	Object
/*     */     // Exception table:
/*     */     //   from	to	target	type
/*     */     //   3	5	3	finally
/*     */     //   10	22	3	finally
/*     */   }
/*     */   
/*     */   /* Error */
/*     */   public void setBExplDatAnniv(boolean paramBoolean)
/*     */   {
/*     */     // Byte code:
/*     */     //   0: goto +6 -> 6
/*     */     //   3: aload_3
/*     */     //   4: monitorexit
/*     */     //   5: athrow
/*     */     //   6: aload_0
/*     */     //   7: dup
/*     */     //   8: astore_3
/*     */     //   9: monitorenter
/*     */     //   10: aload_0
/*     */     //   11: getfield 158	facade/characters/wmedef/PostBeatMixinInfoWME:bExplDatAnniv	Z
/*     */     //   14: istore_2
/*     */     //   15: aload_0
/*     */     //   16: iload_1
/*     */     //   17: putfield 158	facade/characters/wmedef/PostBeatMixinInfoWME:bExplDatAnniv	Z
/*     */     //   20: aload_3
/*     */     //   21: monitorexit
/*     */     //   22: aload_0
/*     */     //   23: getfield 41	facade/characters/wmedef/PostBeatMixinInfoWME:__support	Ljava/beans/PropertyChangeSupport;
/*     */     //   26: ldc -95
/*     */     //   28: iload_2
/*     */     //   29: iload_1
/*     */     //   30: invokevirtual 89	java/beans/PropertyChangeSupport:firePropertyChange	(Ljava/lang/String;ZZ)V
/*     */     //   33: return
/*     */     // Line number table:
/*     */     //   Java source line #321	-> byte code offset #0
/*     */     //   Java source line #322	-> byte code offset #0
/*     */     //   Java source line #323	-> byte code offset #10
/*     */     //   Java source line #324	-> byte code offset #15
/*     */     //   Java source line #326	-> byte code offset #22
/*     */     //   Java source line #327	-> byte code offset #33
/*     */     // Local variable table:
/*     */     //   start	length	slot	name	signature
/*     */     //   0	34	0	this	PostBeatMixinInfoWME
/*     */     //   0	34	1	paramBoolean	boolean
/*     */     //   14	15	2	bool	boolean
/*     */     //   3	18	3	Ljava/lang/Object;	Object
/*     */     // Exception table:
/*     */     //   from	to	target	type
/*     */     //   3	5	3	finally
/*     */     //   10	22	3	finally
/*     */   }
/*     */   
/*     */   /* Error */
/*     */   public void setBRM_Italy(boolean paramBoolean)
/*     */   {
/*     */     // Byte code:
/*     */     //   0: goto +6 -> 6
/*     */     //   3: aload_3
/*     */     //   4: monitorexit
/*     */     //   5: athrow
/*     */     //   6: aload_0
/*     */     //   7: dup
/*     */     //   8: astore_3
/*     */     //   9: monitorenter
/*     */     //   10: aload_0
/*     */     //   11: getfield 164	facade/characters/wmedef/PostBeatMixinInfoWME:bRM_Italy	Z
/*     */     //   14: istore_2
/*     */     //   15: aload_0
/*     */     //   16: iload_1
/*     */     //   17: putfield 164	facade/characters/wmedef/PostBeatMixinInfoWME:bRM_Italy	Z
/*     */     //   20: aload_3
/*     */     //   21: monitorexit
/*     */     //   22: aload_0
/*     */     //   23: getfield 41	facade/characters/wmedef/PostBeatMixinInfoWME:__support	Ljava/beans/PropertyChangeSupport;
/*     */     //   26: ldc -89
/*     */     //   28: iload_2
/*     */     //   29: iload_1
/*     */     //   30: invokevirtual 89	java/beans/PropertyChangeSupport:firePropertyChange	(Ljava/lang/String;ZZ)V
/*     */     //   33: return
/*     */     // Line number table:
/*     */     //   Java source line #336	-> byte code offset #0
/*     */     //   Java source line #337	-> byte code offset #0
/*     */     //   Java source line #338	-> byte code offset #10
/*     */     //   Java source line #339	-> byte code offset #15
/*     */     //   Java source line #341	-> byte code offset #22
/*     */     //   Java source line #342	-> byte code offset #33
/*     */     // Local variable table:
/*     */     //   start	length	slot	name	signature
/*     */     //   0	34	0	this	PostBeatMixinInfoWME
/*     */     //   0	34	1	paramBoolean	boolean
/*     */     //   14	15	2	bool	boolean
/*     */     //   3	18	3	Ljava/lang/Object;	Object
/*     */     // Exception table:
/*     */     //   from	to	target	type
/*     */     //   3	5	3	finally
/*     */     //   10	22	3	finally
/*     */   }
/*     */   
/*     */   /* Error */
/*     */   public void setBFAskDrinks(boolean paramBoolean)
/*     */   {
/*     */     // Byte code:
/*     */     //   0: goto +6 -> 6
/*     */     //   3: aload_3
/*     */     //   4: monitorexit
/*     */     //   5: athrow
/*     */     //   6: aload_0
/*     */     //   7: dup
/*     */     //   8: astore_3
/*     */     //   9: monitorenter
/*     */     //   10: aload_0
/*     */     //   11: getfield 170	facade/characters/wmedef/PostBeatMixinInfoWME:bFAskDrinks	Z
/*     */     //   14: istore_2
/*     */     //   15: aload_0
/*     */     //   16: iload_1
/*     */     //   17: putfield 170	facade/characters/wmedef/PostBeatMixinInfoWME:bFAskDrinks	Z
/*     */     //   20: aload_3
/*     */     //   21: monitorexit
/*     */     //   22: aload_0
/*     */     //   23: getfield 41	facade/characters/wmedef/PostBeatMixinInfoWME:__support	Ljava/beans/PropertyChangeSupport;
/*     */     //   26: ldc -83
/*     */     //   28: iload_2
/*     */     //   29: iload_1
/*     */     //   30: invokevirtual 89	java/beans/PropertyChangeSupport:firePropertyChange	(Ljava/lang/String;ZZ)V
/*     */     //   33: return
/*     */     // Line number table:
/*     */     //   Java source line #350	-> byte code offset #0
/*     */     //   Java source line #351	-> byte code offset #0
/*     */     //   Java source line #352	-> byte code offset #10
/*     */     //   Java source line #353	-> byte code offset #15
/*     */     //   Java source line #355	-> byte code offset #22
/*     */     //   Java source line #356	-> byte code offset #33
/*     */     // Local variable table:
/*     */     //   start	length	slot	name	signature
/*     */     //   0	34	0	this	PostBeatMixinInfoWME
/*     */     //   0	34	1	paramBoolean	boolean
/*     */     //   14	15	2	bool	boolean
/*     */     //   3	18	3	Ljava/lang/Object;	Object
/*     */     // Exception table:
/*     */     //   from	to	target	type
/*     */     //   3	5	3	finally
/*     */     //   10	22	3	finally
/*     */   }
/*     */   
/*     */   /* Error */
/*     */   public void setBPhoneCall(boolean paramBoolean)
/*     */   {
/*     */     // Byte code:
/*     */     //   0: goto +6 -> 6
/*     */     //   3: aload_3
/*     */     //   4: monitorexit
/*     */     //   5: athrow
/*     */     //   6: aload_0
/*     */     //   7: dup
/*     */     //   8: astore_3
/*     */     //   9: monitorenter
/*     */     //   10: aload_0
/*     */     //   11: getfield 176	facade/characters/wmedef/PostBeatMixinInfoWME:bPhoneCall	Z
/*     */     //   14: istore_2
/*     */     //   15: aload_0
/*     */     //   16: iload_1
/*     */     //   17: putfield 176	facade/characters/wmedef/PostBeatMixinInfoWME:bPhoneCall	Z
/*     */     //   20: aload_3
/*     */     //   21: monitorexit
/*     */     //   22: aload_0
/*     */     //   23: getfield 41	facade/characters/wmedef/PostBeatMixinInfoWME:__support	Ljava/beans/PropertyChangeSupport;
/*     */     //   26: ldc -77
/*     */     //   28: iload_2
/*     */     //   29: iload_1
/*     */     //   30: invokevirtual 89	java/beans/PropertyChangeSupport:firePropertyChange	(Ljava/lang/String;ZZ)V
/*     */     //   33: return
/*     */     // Line number table:
/*     */     //   Java source line #365	-> byte code offset #0
/*     */     //   Java source line #366	-> byte code offset #0
/*     */     //   Java source line #367	-> byte code offset #10
/*     */     //   Java source line #368	-> byte code offset #15
/*     */     //   Java source line #370	-> byte code offset #22
/*     */     //   Java source line #371	-> byte code offset #33
/*     */     // Local variable table:
/*     */     //   start	length	slot	name	signature
/*     */     //   0	34	0	this	PostBeatMixinInfoWME
/*     */     //   0	34	1	paramBoolean	boolean
/*     */     //   14	15	2	bool	boolean
/*     */     //   3	18	3	Ljava/lang/Object;	Object
/*     */     // Exception table:
/*     */     //   from	to	target	type
/*     */     //   3	5	3	finally
/*     */     //   10	22	3	finally
/*     */   }
/*     */ }


/* Location:              C:\Program Files (x86)\Extrieur\util\classes\!\facade\characters\wmedef\PostBeatMixinInfoWME.class
 * Java compiler version: 4 (48.0)
 * JD-Core Version:       0.7.1
 */